ImmunoViewer/__init__.py
ImmunoViewer/_version.py
ImmunoViewer/server.py
ImmunoViewer/watch_folder_docker.py
ImmunoViewer/watch_folder_watchdog.py
ImmunoViewer/client/favicon.ico
ImmunoViewer/client/index.html
ImmunoViewer/client/assets/SlideViewer-13d6bf50.css
ImmunoViewer/client/assets/SlideViewer-44b07d73.js
ImmunoViewer/client/assets/SlideViewer-4db2fbd9.js
ImmunoViewer/client/assets/SlideViewer-73b8a8f8.css
ImmunoViewer/client/assets/SlideViewer-a4917311.css
ImmunoViewer/client/assets/SlideViewer-acc75342.js
ImmunoViewer/client/assets/SlideViewer-c345c42b.js
ImmunoViewer/client/assets/SlideViewer-cac74aba.js
ImmunoViewer/client/assets/SlideViewer-d9842cde.js
ImmunoViewer/client/assets/SlideViewer-dfaf7abb.js
ImmunoViewer/client/assets/SlideViewerNew-2d6a5d9a.js
ImmunoViewer/client/assets/SlideViewerNew-7aec11c6.js
ImmunoViewer/client/assets/SlideViewerNew-e1bcd4c6.css
ImmunoViewer/client/assets/SlideViewerNew-ec6e481a.js
ImmunoViewer/client/assets/index-16c8f7df.js
ImmunoViewer/client/assets/index-1a44217b.js
ImmunoViewer/client/assets/index-26efefc2.js
ImmunoViewer/client/assets/index-36ec0fef.js
ImmunoViewer/client/assets/index-38ec41fb.css
ImmunoViewer/client/assets/index-8ddde4e4.js
ImmunoViewer/client/assets/index-ab2b0f89.js
ImmunoViewer/client/assets/index-d030ddc6.js
ImmunoViewer/client/assets/index-d0c0c412.js
ImmunoViewer/client/assets/index-e299d4d6.js
ImmunoViewer/client/assets/index-e540ed02.js
ImmunoViewer/client/assets/index-f65d5671.css
ImmunoViewer/client/assets/materialdesignicons-webfont-67d24abe.eot
ImmunoViewer/client/assets/materialdesignicons-webfont-80bb28b3.woff
ImmunoViewer/client/assets/materialdesignicons-webfont-a58ecb54.ttf
ImmunoViewer/client/assets/materialdesignicons-webfont-c1c004a9.woff2
ImmunoViewer/client/images/fullpage_grouphover.png
ImmunoViewer/client/images/fullpage_hover.png
ImmunoViewer/client/images/fullpage_pressed.png
ImmunoViewer/client/images/fullpage_rest.png
ImmunoViewer/client/images/home_grouphover.png
ImmunoViewer-0.2.5.dist-info/LICENSE.md
ImmunoViewer-0.2.5.dist-info/METADATA
ImmunoViewer-0.2.5.dist-info/WHEEL
ImmunoViewer-0.2.5.dist-info/entry_points.txt
ImmunoViewer-0.2.5.dist-info/top_level.txt
ImmunoViewer-0.2.5.dist-info/RECORD
