Metadata-Version: 2.1
Name: ImmunoViewer
Version: 0.2.5
Summary: Explore and annotate your multi-channel large TIF files with this user-friendly viewer.
Author-email: David van IJzendoorn <davidvanijzendoorn@gmail.com>
License: Creative Commons Attribution-NonCommercial 4.0 International License
Project-URL: Homepage, https://github.com/davidvi/ImmunoViewer
Project-URL: Source, https://github.com/davidvi/ImmunoViewer
Project-URL: Bug Reports, https://github.com/davidvi/ImmunoViewer/issues
Project-URL: Documentation, https://github.com/davidvi/ImmunoViewer
Keywords: big tif,immuno,viewer,annotate,annotation,discover,discovery,image,images,tif,tiff,multi-channel,multi c
Classifier: Development Status :: 5 - Production/Stable
Classifier: Intended Audience :: Developers
Classifier: Intended Audience :: End Users/Desktop
Classifier: Programming Language :: Python :: 3
Classifier: Programming Language :: Python :: 3.6
Classifier: Programming Language :: Python :: 3.7
Classifier: Programming Language :: Python :: 3.8
Classifier: Programming Language :: Python :: 3.9
Classifier: Programming Language :: Python :: 3.10
Classifier: Programming Language :: Python :: 3.11
Classifier: Programming Language :: Python :: 3.12
Classifier: Programming Language :: Python :: 3 :: Only
Classifier: License :: OSI Approved :: MIT License
Classifier: Operating System :: OS Independent
Requires-Python: >=3.8
License-File: LICENSE.md
Requires-Dist: click ~=8.1.3
Requires-Dist: contourpy ~=1.0.7
Requires-Dist: cycler ~=0.11.0
Requires-Dist: fonttools ~=4.39.0
Requires-Dist: itsdangerous ~=2.1.2
Requires-Dist: jinja2 ~=3.1.2
Requires-Dist: kiwisolver ~=1.4.4
Requires-Dist: markupsafe ~=2.1.2
Requires-Dist: matplotlib ~=3.7.1
Requires-Dist: numpy ~=1.24.2
Requires-Dist: pillow ~=9.4.0
Requires-Dist: pyparsing ~=3.0.9
Requires-Dist: werkzeug ~=2.2.3
Requires-Dist: watchdog ~=4.0.0
Requires-Dist: aicsimageio ~=4.14.0
Requires-Dist: opencv-python ~=4.7.0
Requires-Dist: gunicorn ~=22.0.0
Requires-Dist: fastapi ~=0.110.2
Requires-Dist: uvicorn ~=0.29.0
Requires-Dist: pydantic-settings ~=2.2.1
Provides-Extra: test
Requires-Dist: pytest >=6.0 ; extra == 'test'
Requires-Dist: mock >=4.0 ; extra == 'test'
